quasemrfscangui/__init__.py
quasemrfscangui/quasemrfscangui.py
quasemrfscangui_tspspi-0.0.3.dist-info/LICENSE.md
quasemrfscangui_tspspi-0.0.3.dist-info/METADATA
quasemrfscangui_tspspi-0.0.3.dist-info/WHEEL
quasemrfscangui_tspspi-0.0.3.dist-info/entry_points.txt
quasemrfscangui_tspspi-0.0.3.dist-info/top_level.txt
quasemrfscangui_tspspi-0.0.3.dist-info/RECORD
